[{\n  "id": 1,\n  "name": "Ultra Mega",\n  "slug": "ultra-mega",\n  "sector": "Materiais Industriais",\n  "practices": ["painéis solares","coleta seletiva","iluminação LED"],\n  "certifications": [],\n  "selo": "Selo Verde (Jornal do Meio Ambiente)",\n  "website": "",\n  "contact_email": "",\n  "contact_phone": "",\n  "city": "",\n  "state": "",\n  "logo_filename": "assets/logos/ultra-mega.jpeg",\n  "alt_text": "Logo Ultra Mega",\n  "permission_use": "sim",\n  "notes": ""\n},\n  {\n    "id": 2,\n    "name": "Brascon Gestão Ambiental",\n    "slug": "brascon",\n    "sector": "Gestão Ambiental",\n    "practices": ["consultoria ambiental","gestão de resíduos"],\n    "certifications": [],\n    "selo": "",\n    "website": "https://example.com",\n    "contact_email": "",\n    "contact_phone": "",\n    "city": "",\n    "state": "",\n    "logo_filename": "assets/logos/brascon.jpeg",\n    "alt_text": "Logo Brascon",\n    "permission_use": "sim",\n    "notes": ""\n  },\n  {\n    "id": 3,\n    "name": "Green Paperless",\n    "slug": "green-paperless",\n    "sector": "Soluções sem papel",\n    "practices": ["digitalização","redução de papel"],\n    "certifications": [],\n    "selo": "",\n    "website": "https://example.com",\n    "contact_email": "",\n    "contact_phone": "",\n    "city": "",\n    "state": "",\n    "logo_filename": "assets/logos/green-paperless.jpeg",\n    "alt_text": "Logo Green Paperless",\n    "permission_use": "sim",\n    "notes": ""\n  },\n  {\n    "id": 4,\n    "name": "EcoAlternativa",\n    "slug": "ecoalternativa",\n    "sector": "Assessoria Ambiental",\n    "practices": ["assessoria","licenciamentos","monitoramento"],\n    "certifications": [],\n    "selo": "",\n    "website": "https://example.com",\n    "contact_email": "",\n    "contact_phone": "",\n    "city": "",\n    "state": "",\n    "logo_filename": "assets/logos/eco-alternativa.jpeg",\n    "alt_text": "Logo EcoAlternativa",\n    "permission_use": "sim",\n    "notes": ""\n  },\n  {\n    "id": 5,\n    "name": "BIOWASH INDUSTRIA",\n    "slug": "biowash",\n    "sector": "Produtos de Limpeza",\n    "practices": ["produtos biodegradáveis","fórmulas ecológicas"],\n    "certifications": [],\n    "selo": "",\n    "website": "https://example.com",\n    "contact_email": "",\n    "contact_phone": "",\n    "city": "",\n    "state": "",\n    "logo_filename": "assets/logos/biowash.jfif",\n    "alt_text": "Logo BIOWASH",\n    "permission_use": "sim",\n    "notes": ""\n  },\n  {\n    "id": 6,\n    "name": "Boca da Mata",\n    "slug": "boca-da-mata",\n    "sector": "Produtos Naturais",\n    "practices": ["produtos naturais e orgânicos"],\n    "certifications": [],\n    "selo": "",\n    "website": "https://example.com",\n    "contact_email": "",\n    "contact_phone": "",\n    "city": "",\n    "state": "",\n    "logo_filename": "assets/logos/boca-da-mata.jpeg",\n    "alt_text": "Logo Boca da Mata",\n    "permission_use": "sim",\n    "notes": ""\n  },\n  {\n    "id": 7,\n    "name": "Comadre Fulozinha",\n    "slug": "comadre-fulozinha",\n    "sector": "Produtos Orgânicos",\n    "practices": ["produtos orgânicos","agroecologia"],\n    "certifications": [],\n    "selo": "",\n    "website": "https://example.com",\n    "contact_email": "",\n    "contact_phone": "",\n    "city": "",\n    "state": "",\n    "logo_filename": "assets/logos/comadre-fulozinha.jpeg",\n    "alt_text": "Logo Comadre Fulozinha",\n    "permission_use": "sim",\n    "notes": ""\n  },\n  {\n    "id": 8,\n    "name": "Centro de Reciclagem do Nordeste",\n    "slug": "crn",\n    "sector": "Reciclagem",\n    "practices": ["reciclagem","gestão de resíduos"],\n    "certifications": [],\n    "selo": "",\n    "website": "https://example.com",\n    "contact_email": "",\n    "contact_phone": "",\n    "city": "",\n    "state": "",\n    "logo_filename": "assets/logos/crn.jpeg",\n    "alt_text": "Logo CRN",\n    "permission_use": "sim",\n    "notes": ""\n  },\n  {\n    "id": 9,\n    "name": "DescTec Natureza e Tecnologia",\n    "slug": "desctec",\n    "sector": "Reciclagem/Recuperação de Eletrônicos",\n    "practices": ["remanufatura","reciclagem de eletrônicos"],\n    "certifications": [],\n    "selo": "",\n    "website": "https://example.com",\n    "contact_email": "",\n    "contact_phone": "",\n    "city": "",\n    "state": "",\n    "logo_filename": "assets/logos/desctec.jpeg",\n    "alt_text": "Logo DescTec",\n    "permission_use": "sim",\n    "notes": ""\n  },\n  {\n    "id": 10,\n    "name": "Ecobras Gestão Ambiental",\n    "slug": "ecobras",\n    "sector": "Reciclagem/Gestão Ambiental",\n    "practices": ["gestão de resíduos","coleta seletiva"],\n    "certifications": [],\n    "selo": "",\n    "website": "https://example.com",\n    "contact_email": "",\n    "contact_phone": "",\n    "city": "",\n    "state": "",\n    "logo_filename": "assets/logos/ecobras.jpeg",\n    "alt_text": "Logo Ecobras",\n    "permission_use": "sim",\n    "notes": ""\n  },\n  {\n    "id": 11,\n    "name": "Fazenda Guata Porã",\n    "slug": "fazenda-guata-pora",\n    "sector": "Agricultura Orgânica",\n    "practices": ["produção orgânica","agricultura sustentável"],\n    "certifications": [],\n    "selo": "",\n    "website": "",\n    "contact_email": "",\n    "contact_phone": "",\n    "city": "",\n    "state": "",\n    "logo_filename": "assets/logos/fazenda-guata-pora-organico-sem-marca.jpeg",\n    "alt_text": "Logo Fazenda Guata Porã",\n    "permission_use": "sim",\n    "notes": ""\n  },\n  {\n    "id": 12,\n    "name": "Recicle Soluções Ambientais",\n    "slug": "recicle",\n    "sector": "Reciclagem",\n    "practices": ["coleta e reciclagem","logística reversa"],\n    "certifications": [],\n    "selo": "",\n    "website": "https://example.com",\n    "contact_email": "",\n    "contact_phone": "",\n    "city": "",\n    "state": "",\n    "logo_filename": "assets/logos/recicle.jpeg",\n    "alt_text": "Logo Recicle",\n    "permission_use": "sim",\n    "notes": ""\n  },\n  {\n    "id": 13,\n    "name": "Recigreen Tecnologias",\n    "slug": "recigreen",\n    "sector": "Tecnologia Verde",\n    "practices": ["tecnologia verde","reciclagem"],\n    "certifications": [],\n    "selo": "",\n    "website": "https://example.com",\n    "contact_email": "",\n    "contact_phone": "",\n    "city": "",\n    "state": "",\n    "logo_filename": "assets/logos/recigreen.jpeg",\n    "alt_text": "Logo Recigreen",\n    "permission_use": "sim",\n    "notes": ""\n  },\n  {\n    "id": 14,\n    "name": "Reecicle",\n    "slug": "reecicle",\n    "sector": "Reciclagem",\n    "practices": ["reciclagem de eletrônicos","logística reversa"],\n    "certifications": [],\n    "selo": "",\n    "website": "https://example.com",\n    "contact_email": "",\n    "contact_phone": "",\n    "city": "",\n    "state": "",\n    "logo_filename": "assets/logos/reecicle.jpeg",\n    "alt_text": "Logo Reecicle",\n    "permission_use": "sim",\n    "notes": ""\n  },\n  {\n    "id": 15,\n    "name": "Sítio Boa Esperança / Ecobio",\n    "slug": "sitio-boa-esperanca-ecobio",\n    "sector": "Agricultura Orgânica",\n    "practices": ["produtos orgânicos"],\n    "certifications": [],\n    "selo": "",\n    "website": "",\n    "contact_email": "",\n    "contact_phone": "",\n    "city": "",\n    "state": "",\n    "logo_filename": "assets/logos/sitio-boa-esperanca-ecobio.jpeg",\n    "alt_text": "Logo Sítio Boa Esperança / Ecobio",\n    "permission_use": "sim",\n    "notes": ""\n  },\n  {\n    "id": 16,\n    "name": "Korin",\n    "slug": "korin",\n    "sector": "Alimentos",\n    "practices": ["alimentos orgânicos","produção sustentável"],\n    "certifications": [],\n    "selo": "",\n    "website": "https://example.com",\n    "contact_email": "",\n    "contact_phone": "",\n    "city": "",\n    "state": "",\n    "logo_filename": "assets/logos/korin-native.jpeg",\n    "alt_text": "Logo Korin",\n    "permission_use": "sim",\n    "notes": ""\n  },\n  {\n    "id": 17,\n    "name": "Native",\n    "slug": "native",\n    "sector": "Alimentos",\n    "practices": ["alimentos naturais","produtos sustentáveis"],\n    "certifications": [],\n    "selo": "",\n    "website": "https://example.com",\n    "contact_email": "",\n    "contact_phone": "",\n    "city": "",\n    "state": "",\n    "logo_filename": "assets/logos/korin-native.jpeg",\n    "alt_text": "Logo Native",\n    "permission_use": "sim",\n    "notes": ""\n  },\n  {\n    "id": 18,\n    "name": "ERS Brazil",\n    "slug": "ers-brazil",\n    "sector": "Reciclagem de Eletrônicos",\n    "practices": ["descarte de ativos de TI","remanufatura","reciclagem de equipamentos eletrônicos"],\n    "certifications": ["ISO 14001","ISO 9001","ISO 45001","R2v3"],\n    "selo": "",\n    "website": "https://ersbrazil.com",\n    "contact_email": "",\n    "contact_phone": "",\n    "city": "",\n    "state": "",\n    "logo_filename": "assets/logos/Logo-ERS.png",\n    "alt_text": "Logo ERS Brazil",\n    "permission_use": "sim",\n    "notes": ""\n  },\n  {\n    "id": 19,\n    "name": "NTC Company",\n    "slug": "ntc",\n    "sector": "Moldes e Peças Plásticas",\n    "practices": ["painéis solares","coleta seletiva","torneiras temporizadoras","iluminação LED eficiente"],\n    "certifications": [],\n    "selo": "Selo Verde (Jornal do Meio Ambiente)",\n    "website": "",\n    "contact_email": "",\n    "contact_phone": "",\n    "city": "",\n    "state": "",\n    "logo_filename": "assets/logos/ntc.png",\n    "alt_text": "Logo NTC Company",\n    "permission_use": "sim",\n    "notes": ""\n  },\n  {\n    "id": 20,\n    "name": "Reciclagem Brasil",\n    "slug": "reciclagem-brasil",\n    "sector": "Reciclagem",\n    "practices": ["reciclagem","gestão de resíduos"],\n    "certifications": [],\n    "selo": "",\n    "website": "",\n    "contact_email": "",\n    "contact_phone": "",\n    "city": "",\n    "state": "",\n    "logo_filename": "assets/logos/reciclagem-brasil.jpeg",\n    "alt_text": "Logo Reciclagem Brasil",\n    "permission_use": "sim",\n    "notes": ""\n  },\n  {\n    "id": 21,\n    "name": "FBS Construção Civil e Pavimentação S.A.",\n    "slug": "fbs",\n    "sector": "Construção Civil",\n    "practices": ["construção sustentável","pavimentação"],\n    "certifications": [],\n    "selo": "",\n    "website": "",\n    "contact_email": "",\n    "contact_phone": "",\n    "city": "",\n    "state": "",\n    "logo_filename": "assets/logos/logo FBS.jpg",\n    "alt_text": "Logo FBS",\n    "permission_use": "sim",\n    "notes": ""\n  },\n  {\n    "id": 22,\n    "name": "EcoCasa",\n    "slug": "ecocasa",\n    "sector": "Construção Civil",\n    "practices": ["construção sustentável","materiais reciclados"],\n    "certifications": [],\n    "selo": "",\n    "website": "",\n    "contact_email": "",\n    "contact_phone": "",\n    "city": "",\n    "state": "",\n    "logo_filename": "assets/logos/a logo ecocasa.jfif",\n    "alt_text": "Logo EcoCasa",\n    "permission_use": "sim",\n    "notes": ""\n  },\n  {\n    "id": 23,\n    "name": "Ibaplac",\n    "slug": "ibaplac",\n    "sector": "Materiais Reciclados",\n    "practices": ["produtos reciclados","materiais para construção"],\n    "certifications": [],\n    "selo": "",\n    "website": "",\n    "contact_email": "",\n    "contact_phone": "",\n    "city": "",\n    "state": "",\n    "logo_filename": "assets/logos/a logo Ibaplac.jfif",\n    "alt_text": "Logo Ibaplac",\n    "permission_use": "sim",\n    "notes": ""\n  },\n  {\n    "id": 24,\n    "name": "Positiva Comercio de Produtos e Serviços Ecológicos S.A.",\n    "slug": "positiva",\n    "sector": "Produtos de Limpeza",\n    "practices": ["produtos ecológicos","detergentes biodegradáveis"],\n    "certifications": [],\n    "selo": "",\n    "website": "",\n    "contact_email": "",\n    "contact_phone": "",\n    "city": "",\n    "state": "",\n    "logo_filename": "assets/logos/logo positiva.jfif",\n    "alt_text": "Logo Positiva",\n    "permission_use": "sim",\n    "notes": ""\n  },\n  {\n    "id": 25,\n    "name": "NOVA RENKO INDUSTRIAL LTDA",\n    "slug": "renko",\n    "sector": "Produtos de Limpeza/Industrial",\n    "practices": ["produtos de limpeza ecológicos"],\n    "certifications": [],\n    "selo": "",\n    "website": "",\n    "contact_email": "",\n    "contact_phone": "",\n    "city": "",\n    "state": "",\n    "logo_filename": "assets/logos/logo Renko.png",\n    "alt_text": "Logo Renko",\n    "permission_use": "sim",\n    "notes": ""\n  },\n  {\n    "id": 26,\n    "name": "Nordeste Ambiental Recife Ltda",\n    "slug": "nordeste-ambiental",\n    "sector": "Serviços Ambientais",\n    "practices": ["serviços de gestão ambiental","consultoria"],\n    "certifications": [],\n    "selo": "",\n    "website": "",\n    "contact_email": "",\n    "contact_phone": "",\n    "city": "",\n    "state": "",\n    "logo_filename": "assets/logos/logo nordeste ambiental.png",\n    "alt_text": "Logo Nordeste Ambiental",\n    "permission_use": "sim",\n    "notes": ""\n  }\n]